{"assets/fonts/carter.ttf":["assets/fonts/carter.ttf"],"assets/fonts/fresh.otf":["assets/fonts/fresh.otf"],"assets/fonts/luck.ttf":["assets/fonts/luck.ttf"],"assets/fonts/robotolight.ttf":["assets/fonts/robotolight.ttf"],"assets/fonts/robotomedium.ttf":["assets/fonts/robotomedium.ttf"],"assets/fonts/robotoregular.ttf":["assets/fonts/robotoregular.ttf"],"assets/fonts/sampiyon.ttf":["assets/fonts/sampiyon.ttf"],"assets/imagers/lists.png":["assets/imagers/lists.png"],"assets/imagers/logo.jpg":["assets/imagers/logo.jpg"],"assets/imagers/selcuk":["assets/imagers/selcuk"],"packages/cupertino_icons/assets/CupertinoIcons.ttf":["packages/cupertino_icons/assets/CupertinoIcons.ttf"],"packages/fluttertoast/assets/toastify.css":["packages/fluttertoast/assets/toastify.css"],"packages/fluttertoast/assets/toastify.js":["packages/fluttertoast/assets/toastify.js"]}